argus/README.md
argus/__init__.py
argus/cli.py
argus/orchestrator.py
argus/py.typed
argus/agents/README.md
argus/agents/__init__.py
argus/agents/base.py
argus/agents/jury.py
argus/agents/moderator.py
argus/agents/refuter.py
argus/agents/specialist.py
argus/cdag/README.md
argus/cdag/__init__.py
argus/cdag/edges.py
argus/cdag/graph.py
argus/cdag/nodes.py
argus/cdag/propagation.py
argus/core/README.md
argus/core/__init__.py
argus/core/config.py
argus/core/models.py
argus/core/llm/__init__.py
argus/core/llm/anthropic.py
argus/core/llm/azure_openai.py
argus/core/llm/base.py
argus/core/llm/bedrock.py
argus/core/llm/cerebras.py
argus/core/llm/cloudflare.py
argus/core/llm/cohere.py
argus/core/llm/databricks.py
argus/core/llm/deepseek.py
argus/core/llm/fireworks.py
argus/core/llm/gemini.py
argus/core/llm/groq.py
argus/core/llm/huggingface.py
argus/core/llm/litellm.py
argus/core/llm/llamacpp.py
argus/core/llm/mistral.py
argus/core/llm/nvidia.py
argus/core/llm/ollama.py
argus/core/llm/openai.py
argus/core/llm/perplexity.py
argus/core/llm/registry.py
argus/core/llm/replicate.py
argus/core/llm/sambanova.py
argus/core/llm/snowflake.py
argus/core/llm/together.py
argus/core/llm/vertex.py
argus/core/llm/vllm.py
argus/core/llm/watsonx.py
argus/core/llm/xai.py
argus/debate/README.md
argus/decision/README.md
argus/decision/__init__.py
argus/decision/bayesian.py
argus/decision/calibration.py
argus/decision/eig.py
argus/decision/planner.py
argus/durable/__init__.py
argus/durable/checkpointer.py
argus/durable/config.py
argus/durable/state.py
argus/durable/tasks.py
argus/durable/workflow.py
argus/embeddings/README.md
argus/embeddings/__init__.py
argus/embeddings/azure.py
argus/embeddings/base.py
argus/embeddings/bedrock.py
argus/embeddings/cohere.py
argus/embeddings/fastembed.py
argus/embeddings/fireworks.py
argus/embeddings/google.py
argus/embeddings/huggingface.py
argus/embeddings/jina.py
argus/embeddings/mistral.py
argus/embeddings/nomic.py
argus/embeddings/nvidia.py
argus_debate_ai-2.1.1.dist-info/licenses/LICENSE
argus_debate_ai-2.1.1.dist-info/METADATA
argus_debate_ai-2.1.1.dist-info/WHEEL
argus_debate_ai-2.1.1.dist-info/entry_points.txt
argus_debate_ai-2.1.1.dist-info/top_level.txt
argus_debate_ai-2.1.1.dist-info/RECORD
