Metadata-Version: 2.4
Name: argus-debate-ai
Version: 2.1.1
Summary: ARGUS: Production-ready multi-agent AI debate framework with RAG, Bayesian reasoning, provenance tracking, and advanced LLM orchestration for scientific discovery, fact-checking, and evidence-based decision-making
Author-email: "Ankush Pandey, Rishi Ghodawat, Ronit Mehta" <mehtaronit702@gmail.com>
Maintainer-email: ARGUS Team <mehtaronit702@gmail.com>
License: MIT
Project-URL: Homepage, https://github.com/Ronit26Mehta/argus-ai-debate
Project-URL: Documentation, https://github.com/Ronit26Mehta/argus-ai-debate#readme
Project-URL: Repository, https://github.com/Ronit26Mehta/argus-ai-debate
Project-URL: Issues, https://github.com/Ronit26Mehta/argus-ai-debate/issues
Project-URL: Changelog, https://github.com/Ronit26Mehta/argus-ai-debate/releases
Keywords: ai,artificial-intelligence,multi-agent,debate,reasoning,llm,gpt,claude,gemini,scientific-discovery,research,decision-making,fact-checking,verification,rag,retrieval-augmented-generation,embeddings,vector-search,knowledge-graph,bayesian-inference,argumentation,provenance,langchain-alternative,agent-framework,llm-framework,openai,anthropic,ollama
Classifier: Development Status :: 6 - Mature
Classifier: Intended Audience :: Developers
Classifier: Intended Audience :: Science/Research
Classifier: Intended Audience :: Information Technology
Classifier: Intended Audience :: Education
Classifier: License :: OSI Approved :: MIT License
Classifier: Operating System :: OS Independent
Classifier: Operating System :: POSIX :: Linux
Classifier: Operating System :: Microsoft :: Windows
Classifier: Operating System :: MacOS
Classifier: Programming Language :: Python :: 3
Classifier: Programming Language :: Python :: 3.11
Classifier: Programming Language :: Python :: 3.12
Classifier: Programming Language :: Python :: 3.13
Classifier: Programming Language :: Python :: Implementation :: CPython
Classifier: Topic :: Scientific/Engineering :: Artificial Intelligence
Classifier: Topic :: Scientific/Engineering :: Information Analysis
Classifier: Topic :: Software Development :: Libraries :: Python Modules
Classifier: Topic :: Text Processing :: Linguistic
Classifier: Topic :: Internet :: WWW/HTTP :: Indexing/Search
Classifier: Framework :: AsyncIO
Classifier: Typing :: Typed
Classifier: Environment :: Console
Classifier: Environment :: Web Environment
Classifier: Natural Language :: English
Requires-Python: >=3.11
License-File: LICENSE
Requires-Dist: pydantic<3.0,>=2.0
Requires-Dist: pydantic-settings<3.0,>=2.0
Requires-Dist: numpy<3.0,>=1.24
Requires-Dist: scipy<2.0,>=1.10
Requires-Dist: networkx<4.0,>=3.0
Requires-Dist: litellm<2.0,>=1.40
Requires-Dist: openai<2.0,>=1.30
Requires-Dist: anthropic<1.0,>=0.25
Requires-Dist: google-generativeai<1.0,>=0.5
Requires-Dist: sentence-transformers<3.0,>=2.2
Requires-Dist: rank-bm25<1.0,>=0.2
Requires-Dist: faiss-cpu<2.0,>=1.7
Requires-Dist: pymupdf<2.0,>=1.23
Requires-Dist: beautifulsoup4<5.0,>=4.12
Requires-Dist: lxml<6.0,>=4.9
Requires-Dist: chardet<6.0,>=5.0
Requires-Dist: click<9.0,>=8.0
Requires-Dist: rich<14.0,>=13.0
Requires-Dist: python-dotenv<2.0,>=1.0
Requires-Dist: httpx<1.0,>=0.25
Requires-Dist: tenacity<9.0,>=8.2
Requires-Dist: tiktoken<1.0,>=0.5
Requires-Dist: requests<3.0,>=2.31
Requires-Dist: textual<1.0,>=0.47
Provides-Extra: dev
Requires-Dist: pytest<9.0,>=7.4; extra == "dev"
Requires-Dist: pytest-asyncio<1.0,>=0.21; extra == "dev"
Requires-Dist: pytest-cov<6.0,>=4.1; extra == "dev"
Requires-Dist: black<25.0,>=23.0; extra == "dev"
Requires-Dist: ruff<1.0,>=0.1; extra == "dev"
Requires-Dist: mypy<2.0,>=1.5; extra == "dev"
Requires-Dist: pre-commit<4.0,>=3.4; extra == "dev"
Provides-Extra: ollama
Requires-Dist: ollama<1.0,>=0.2; extra == "ollama"
Provides-Extra: llamacpp
Requires-Dist: llama-cpp-python<1.0,>=0.2; extra == "llamacpp"
Provides-Extra: cohere
Requires-Dist: cohere<6.0,>=5.0; extra == "cohere"
Provides-Extra: mistral
Requires-Dist: mistralai<1.0,>=0.4; extra == "mistral"
Provides-Extra: groq
Requires-Dist: groq<1.0,>=0.4; extra == "groq"
Provides-Extra: together
Requires-Dist: together<2.0,>=1.0; extra == "together"
Provides-Extra: voyage
Requires-Dist: voyageai<1.0,>=0.2; extra == "voyage"
Provides-Extra: bedrock
Requires-Dist: boto3<2.0,>=1.34; extra == "bedrock"
Provides-Extra: azure
Provides-Extra: vertex
Requires-Dist: google-cloud-aiplatform<2.0,>=1.40; extra == "vertex"
Provides-Extra: embeddings
Requires-Dist: fastembed<1.0,>=0.2; extra == "embeddings"
Requires-Dist: cohere<6.0,>=5.0; extra == "embeddings"
Requires-Dist: voyageai<1.0,>=0.2; extra == "embeddings"
Requires-Dist: nomic<4.0,>=3.0; extra == "embeddings"
Provides-Extra: tools
Requires-Dist: duckduckgo-search<6.0,>=5.0; extra == "tools"
Requires-Dist: wikipedia<2.0,>=1.4; extra == "tools"
Requires-Dist: arxiv<3.0,>=2.1; extra == "tools"
Requires-Dist: tavily-python<1.0,>=0.3; extra == "tools"
Requires-Dist: PyGithub<3.0,>=2.1; extra == "tools"
Requires-Dist: youtube-transcript-api<1.0,>=0.6; extra == "tools"
Requires-Dist: sqlalchemy<3.0,>=2.0; extra == "tools"
Requires-Dist: pandas<3.0,>=2.0; extra == "tools"
Requires-Dist: yfinance<1.0,>=0.2; extra == "tools"
Provides-Extra: plotting
Requires-Dist: matplotlib<4.0,>=3.7; extra == "plotting"
Requires-Dist: seaborn<1.0,>=0.12; extra == "plotting"
Requires-Dist: plotly<6.0,>=5.15; extra == "plotting"
Provides-Extra: terminal
Requires-Dist: textual<1.0,>=0.47; extra == "terminal"
Requires-Dist: pyinstaller<7.0,>=6.0; extra == "terminal"
Provides-Extra: all
Requires-Dist: argus-debate-ai[dev]; extra == "all"
Requires-Dist: argus-debate-ai[ollama]; extra == "all"
Requires-Dist: argus-debate-ai[cohere]; extra == "all"
Requires-Dist: argus-debate-ai[mistral]; extra == "all"
Requires-Dist: argus-debate-ai[groq]; extra == "all"
Requires-Dist: argus-debate-ai[tools]; extra == "all"
Requires-Dist: argus-debate-ai[embeddings]; extra == "all"
Requires-Dist: argus-debate-ai[plotting]; extra == "all"
Dynamic: license-file
